elegantrl/__init__.py
elegantrl/agent.py
elegantrl/demo.py
elegantrl/env.py
elegantrl/evaluator.py
elegantrl/net.py
elegantrl/replay.py
elegantrl/run.py
elegantrl/agents/AgentA2C.py
elegantrl/agents/AgentBase.py
elegantrl/agents/AgentDDPG.py
elegantrl/agents/AgentDQN.py
elegantrl/agents/AgentDoubleDQN.py
elegantrl/agents/AgentMADDPG.py
elegantrl/agents/AgentMAPPO.py
elegantrl/agents/AgentMATD3.py
elegantrl/agents/AgentPPO.py
elegantrl/agents/AgentQMix.py
elegantrl/agents/AgentREDQ.py
elegantrl/agents/AgentSAC.py
elegantrl/agents/AgentStep1AC.py
elegantrl/agents/AgentTD3.py
elegantrl/agents/AgentVDN.py
elegantrl/agents/__init__.py
elegantrl/agents/net.py
elegantrl/envs/CarRacingFix.py
elegantrl/envs/ChasingEnv.py
elegantrl/envs/DownLinkEnv.py
elegantrl/envs/Gym.py
elegantrl/envs/IsaacGym.py
elegantrl/envs/Stock_Trading_Env.py
elegantrl/envs/__init__.py
elegantrl/envs/gym_utils.py
elegantrl/envs/FinRL/FinRL.py
elegantrl/envs/FinRL/StockTrading.py
elegantrl/envs/FinRL/__init__.py
elegantrl/envs/starcraft/StarCraft2Env.py
elegantrl/envs/starcraft/__init__.py
elegantrl/envs/starcraft/smac_maps.py
elegantrl/envs/utils/__init__.py
elegantrl/envs/utils/config.py
elegantrl/envs/utils/marl_utils.py
elegantrl/envs/utils/parse_task.py
elegantrl/envs/utils/process_ppo.py
elegantrl/envs/utils/torch_jit_utils.py
elegantrl/train/__init__.py
elegantrl/train/config.py
elegantrl/train/evaluator.py
elegantrl/train/learner.py
elegantrl/train/replay_buffer.py
elegantrl/train/run.py
elegantrl/train/utils.py
elegantrl/train/worker.py
elegantrl/tutorial/__init__.py
elegantrl/tutorial/agent.py
elegantrl/tutorial/demo.py
elegantrl/tutorial/net.py
elegantrl/tutorial/run.py
elegantrl_helloworld/__init__.py
elegantrl_helloworld/agent.py
elegantrl_helloworld/eRL_demo_PPOinSingleFile.py
elegantrl_helloworld/eRL_demo_SACinSingleFile.py
elegantrl_helloworld/env.py
elegantrl_helloworld/net.py
elegantrl_helloworld/run.py
elegantrl_helloworld/MARL/__init__.py
elegantrl-0.3.3.dist-info/LICENSE
elegantrl-0.3.3.dist-info/METADATA
elegantrl-0.3.3.dist-info/WHEEL
elegantrl-0.3.3.dist-info/top_level.txt
elegantrl-0.3.3.dist-info/RECORD
